{
    "categories": [
      { "id": 1, "title": "SmartPhones" },
      { "id": 2, "title": "Computers" },
      { "id": 3, "title": "Televisions" }
    ],
    "products": [
      {
        "id": 1,
        "catId": 1,
        "title": "Samsung Galaxy Tab Pro S",
        "productCode": "BFFD3577",
        "image": "../../public/assets/id1smartphone.png",
        "price": 579,
        "sku": "577318",
        "description": "Samsung Galaxy TabPro S is based on Windows 10 and packs 128GB of inbuilt storage. The Samsung Galaxy TabPro S measures 198.80 x 290.30 x 6.30mm (height x width x thickness) and weighs 693.00 grams. Connectivity options on the Samsung Galaxy TabPro S include Wi-Fi 802.11 a/b/g/n/ac and GPS.",
        "specs": {"dimensions": "5.8 inches, 84.4 cm2", "capacity": "64GB"},
        "features": ["S-Voice natural language commands and dictation", "Fingerprint (front-mounted), accelerometer, gyro, proximity, compass, barometer, heart rate, SpO2"],
        "stock": 20
      },
      {
        "id": 2,
        "catId": 1,
        "title": "Samsung Galaxy S6",
        "productCode": "CUL55S20",
        "image": "../../public/assets/id2smartphone.png",
        "price": 669,
        "sku": "287494",
        "description": "The Samsung Galaxy S6 presents a radical redesign into the flagship Galaxy S line. With a renewed focus on premium looks and cutting edge specs, the Galaxy S6 sports a Quad HD display, an improved 16MP camera, and - finally - super-fast UFS 2.0 based internal storage starting at 32 GB up to 128 GB. The Galaxy S6 runs on Android 5.0 Lollipop with the company's proprietary TouchWiz skin on top, and it will be the first 64-bit Samsung flagship, coming outfitted with a homemade octa-core chip.",
        "specs": {"dimensions": "5.8 inches, 84.4 cm2", "capacity": "128GBs"},
        "features": ["S-Voice natural language commands and dictation", "Samsung Pay (Visa, MasterCard certified)", "ANT+", "Fingerprint (front-mounted), accelerometer, gyro, proximity, compass, barometer, heart rate, SpO2"],
        "stock": 3
      },
      {
          "id": 3,
          "catId": 1,
          "title": "Iphone X",
          "productCode": "KTLD60X20",
          "image": "../../public/assets/id3smartphone.png",
          "price": 949,
          "sku": "287103",
          "description": "The iPhone X was Apple's flagship 10th anniversary iPhone featuring a 5.8-inch OLED display, facial recognition and 3D camera functionality, a glass body, and an A11 Bionic processor. Launched November 3, 2017, discontinued with the launch of the iPhone XR, XS, and XS Max.",
          "specs": {"dimensions": "5.8 inches, 84.4 cm2", "capacity": "64GB"},
          "features": ["FACE ID", "proximity", "barometer"],
          "stock": 10
      },
      {
        "id": 4,
        "catId": 1,
        "title": "Samsung Galaxy Tab Pro S",
        "productCode": "BFFD3577",
        "image": "../../public/assets/id1smartphone.png",
        "price": 579,
        "sku": "577318",
        "description": "Samsung Galaxy TabPro S is based on Windows 10 and packs 128GB of inbuilt storage. The Samsung Galaxy TabPro S measures 198.80 x 290.30 x 6.30mm (height x width x thickness) and weighs 693.00 grams. Connectivity options on the Samsung Galaxy TabPro S include Wi-Fi 802.11 a/b/g/n/ac and GPS.",
        "specs": {"dimensions": "5.8 inches, 84.4 cm2", "capacity": "64GB"},
        "features": ["S-Voice natural language commands and dictation", "Fingerprint (front-mounted), accelerometer, gyro, proximity, compass, barometer, heart rate, SpO2"],
        "stock": 20
      },
      {
        "id": 5,
        "catId": 1,
        "title": "Iphone 10",
        "productCode": "KTLD60X20",
        "image": "../../public/assets/id3smartphone.png",
        "price": 749,
        "sku": "287103",
        "description": "The iPhone X was Apple's flagship 10th anniversary iPhone featuring a 5.8-inch OLED display, facial recognition and 3D camera functionality, a glass body, and an A11 Bionic processor. Launched November 3, 2017, discontinued with the launch of the iPhone XR, XS, and XS Max.",
        "specs": {"dimensions": "5.8 inches, 84.4 cm2", "capacity": "64GB"},
        "features": ["FACE ID", "proximity", "barometer"],
        "stock": 10
      },
      {
          "id": 6,
          "catId": 3,
          "title": "SAMSUNG UE50TU7020KXXU 50\" Smart 4K Ultra HD HDR LED TV",
          "productCode": "UE50TU7020KXXU",
          "image": "M10213562_001.jfif",
          "price": 389,
          "sku": "670811",
          "description": "Glorious colour\n\nDon\\'t settle for anything less than crystal clear colour. The Samsung UE50TU7020KXXU 50\" Smart 4K Ultra HD HDR LED TV delivers <b>pure colours, sharp contrast, and brilliant brightness</b>. HDR displays the <b>brightest and darkest colours</b> in each frame, so everything from dimly lit dialogue scenes to nature documentaries look vivid and realistic.\n\nA smarter TV\n\nYou\\'ve got one of the largest collections of 4K content and catch-up apps at your fingertips, including Apple TV, Netflix, and Disney+, so you\\'ll never be stuck for something to watch.\n\nImmersive sound\n\nAdaptive Sound automatically adjusts to what you're watching, so your entertainment feels more immersive than before.\n\nGame enhancer\n\nEnjoy your favourite console games with picture and sound that adapts as fast as your game. You won't miss a moment thanks to incredibly low lag rates.\n\nPremium One Remote\n\nNo more need to juggle TV, Blu-ray and sound bar remotes. The Premium One Remote Control connects to all your compatible devices. Crank up the volume on your sound bar, play the latest movies on your Blu-ray player, or even browse the internet on your TV, all from one handy remote.",
          "specs": {"dimensions": " TV with stand: 718.6 x 1115.8 x 250.2 mm (H x W x D) - TV: 643.7 x 1115.8 x 59.5 mm (H x W x D) - Boxed: 780 x 1264 x 150 mm (H x W x D)"},
          "features": ["Crystal display for long-lasting colour & sharp contrast", "Crystal Processor 4K for the best 4K picture & targeted sound", "Picture quality : 2000 PQI", "HDR : HDR10+ / Hybrid Log-Gamma (HLG)", "Catch-up TV & 4K streaming", "TV PLUS", "HDMI 2.0a x 2"],
          "stock": 5
      },
      {
          "id": 7,
          "catId": 3,
          "title": "LG 32LM6370PLA 32\" Smart Full HD HDR LED TV",
          "productCode": "32LM6370PLA",
          "image": "10221968.jfif",
          "price": 249,
          "sku": "657462",
          "description": "Give your favourite movies and box sets a new lease of life with the LG 32LM6370PLA 32\" Smart Full HD HDR LED TV.\n\nIts Active HDR technology delivers pinpoint detail by remastering each scene as you watch. That means you'll see the brightest and darkest shades in the same image, and still notice the subtlest differences in colour.\n\nPowerful processor\n\nThe Quad Core processor reduces noise and creates more dynamic colour and contrast. So whether you're catching up with soaps or following your team in the league, everything you watch appears smooth, vibrant and sharp.\n\nEndless entertainment\n\nNever run out of shows and movies to watch. With webOS, there\\'s something to keep the whole family entertained. Binge through the shows everyone\\'s talking about on Netflix and Amazon Prime, discover new music with Spotify or even download games.\n\nAnd with Freeview Play, you get instant access to the past 7 days of TV shows on BBC, ITV, Channel 4 and loads more.\n\nVirtual Surround Sound\n\nWhen you\\'re watching the latest blockbuster or the big game, you want big sound to match the great picture. The LG 32LM6370PLA features Virtual Surround Sound technology, which creates virtual audio channels to give you a more immersive viewing experience.",
          "specs": {"dimensions": "TV with stand: 464 x 736 x 180 mm (H x W x D) - TV: 437 x 736 x 82.9 mm (H x W x D) - Boxed: 510 x 812 x 142 mm (H x W x D)"},
          "features": ["Full-HD resolution - For Sharp Images", "Dynamic Colour Enhancer - More natural colours", "Dolby Audio™ - A movie-like sound experience", "USB Connection - Enjoy more content on your TV", "Simple Yet Sophisticated Design"],
          "stock": 5
      },
      {
          "id": 8,
          "catId": 3,
          "title": "PANASONIC TX40JX800B 40\" Smart 4K Ultra HD HDR LED TV",
          "productCode": "TX40JX800B",
          "image": "M10222398.jfif",
          "price": 399,
          "sku": "704803",
          "description": "The Panasonic TX-40JX800B 40\" Smart 4K Ultra HD HDR LED TV has plenty of HDR technology to bring you the very best viewing. It brings detail to dark areas of the scene and brings bright vibrant colour, perfect for sports or movies. This TV supports a variety of formats, so you can enjoy HDR content from a broad range of sources.\n\nBright Panel Plus provides bright LED backlighting for sharp and crisp images and the certified Dolby Vision technology renders every scene picture-perfect.\n\nAndroid TV\n\nThis TV comes with Android TV OS, meaning everything you enjoy watching is neatly organised and just a button away. You can also organise your home screen for even simpler access.\n\nOptimised for Netflix streaming, the TX-40JX800B has a dedicated Netflix button that takes you straight to your shows. There are also plenty of streaming options to keep you and your family entertained - including Disney+, Prime Video and many more.\n\nSmart assistant\n\nUse Google Assistant to change channels, control the volume or turn your TV on. You can use it to help you to search the Freeview guide, making it even easier to find the shows you love.\n\nFilmmaker Mode with intelligent sensing\n\nElectronics brands and leading movie directors created Filmmaker Mode. A single button sets the film's colour-palette, contrast, aspect ratio and frame rate as the director intended. The picture automatically adjusts even if light levels change.\n\nSurround Sound\n\nOpen up the soundstage to make the soundtrack feel as involving as the big-screen action. Surround Sound helps draw you into what you're watching to feel more involved with the story.\n\nChromecast built-in\n\nEasily cast your favourite movies, music, and more to your TV with Chromecast built-in. Select the content and send it to the TV with a flick of your finger. You'll be able to see the pictures clearly in all their glory",
          "specs": {"dimensions": "TV with stand: 548 x 904 x 174 mm (H x W x D) - TV: 524 x 904 x 65 mm (H x W x D) - Boxed: 619 x 1011 x 131 mm (H x W x D)"},
          "features": ["HCX Picture Processor for accurate contrast & clarity", "Picture quality : 1400 Hz BMR", "HDR : Dolby Vision / HDR10+ / Hybrid Log-Gamma (HLG)", "Catch-up TV & 4K streaming", "Freeview HD with Freeview Play", "HDMI 2.0 x 3"],
          "stock": 8
      },
      {
          "id": 9,
          "catId": 3,
          "title": "PANASONIC TX48JZ1000B 48\" Smart 4K Ultra HD HDR OLED TV",
          "productCode": "TX48JZ1000B",
          "image": "M10226866.jfif",
          "price": 399,
          "sku": "1199",
          "description": "Cinematic OLED Panel\n\nYour favourite sports, games and movies look better than ever on the Panasonic TX-48JZ1000B 48\"Smart 4K Ultra HD HDR OLED TV. The OLED screen creates natural colour and high contrast so you can see real black where it should be.\n\nAuto AI & Dolby Vision IQ\n\nThe HCX Pro AI processor instantly adjusts the colour and contrast to match what you\\'re watching, so you'll automatically get the best possible picture. And Dolby Vision IQ reacts to light levels in your room, giving you picture-perfect images, even on sunny days.\n\nGame Mode Extreme\n\nEnjoy your favourite games without screen tearing or stuttering thanks to OLED display and AMD FreeSync Premium. Featuring HDMI 2.1 with support for high frame rates, VRR and ALLM, the TV delivers super-smooth action with low input lag.\n\nDolby Atmos audio\n\nHear the gentle trickle of rainfall or the roar of planes overhead with Dolby Atmos virtual surround sound. It puts you right at the heart of the action, so you'll get multi-dimensional audio that seems to flow all around you.\n\nSmart TV\n\nWith Google Assistant and Amazon Alexa voice control built in, it\\'s never been easier to find what you want to watch, control your smart home, and get updates personal to you.\n\nImmerse yourself in all your favourite films and shows with apps like Netflix, Prime Video, Disney+ and more. And you can catch up on shows you've missed straight from the TV guide with Freeview Play.",
          "specs": {"dimensions": "TV with stand: 682 x 1069 x 300 mm (H x W x D) - TV: 622 x 1069 x 300 mm (H x W x D) - Boxed: 220 x 1408 x 745 mm (H x W x D)"},
          "features": ["HCX Pro AI Processor for cinematic contrast & clarity", "Cinematic sound with Dolby Atmos", "Picture quality : 120 Hz", "Dolby Vision IQ / HDR10+ / HDR10 / Hybrid Log-Gamma (HLG)", "Catch-up TV & 4K streaming", "Freeview HD with Freeview Play", "HDMI 2.1 x 2 / HDMI 2.0 x 2"],
          "stock": 8
      },
      {
          "id": 10,
          "catId": 3,
          "title": "SAMSUNG UE75TU7020KXXU 75\" Smart 4K Ultra HD HDR LED TV",
          "productCode": "UE75TU7020KXXU",
          "image": "M10213562_008.jfif",
          "price": 779,
          "sku": "M10213562_008.jfif",
          "description": "Glorious colour\n\nDon\\'t settle for anything less than crystal clear colour. The Samsung UE75TU7020KXXU 75\" Smart 4K Ultra HD HDR LED TV delivers pure colours, sharp contrast, and brilliant brightness. HDR displays the brightest and darkest colours in each frame, so everything from dimly lit dialogue scenes to nature documentaries look vivid and realistic.\n\nA smarter TV\n\nYou\\'ve got one of the largest collections of 4K content and catch-up apps at your fingertips, including Apple TV, Netflix, and Disney+, so you\\'ll never be stuck for something to watch.\n\nImmersive sound\n\nAdaptive Sound automatically adjusts to what you're watching, so your entertainment feels more immersive than before.\n\nGame enhancer\n\nEnjoy your favourite console games with picture and sound that adapts as fast as your game. You won't miss a moment thanks to incredibly low lag rates.\n\nPremium One Remote\n\nNo more need to juggle TV, Blu-ray and sound bar remotes. The Premium One Remote Control connects to all your compatible devices. Crank up the volume on your sound bar, play the latest movies on your Blu-ray player, or even browse the internet on your TV, all from one handy remote.",
          "specs": {"dimensions": "TV with stand: 682 x 1069 x 300 mm (H x W x D) - TV: 622 x 1069 x 300 mm (H x W x D) - Boxed: 220 x 1408 x 745 mm (H x W x D)"},
          "features": ["Crystal display for long-lasting colour & sharp contrast", "Crystal Processor 4K for the best 4K picture & targeted sound", "Picture quality : 2000 PQI", "HDR : HDR10+ / Hybrid Log-Gamma (HLG)", "Catch-up TV & 4K streaming", "TV PLUS", "HDMI 2.1 x 2 / HDMI 2.0 x 2"],
          "stock": 16
      }
    ]
  }
  